portia/__init__.py
portia/core.py
portia/correction.py
portia/dataset.py
portia/end_to_end.py
portia/exceptions.py
portia/la.py
portia/optim/__init__.py
portia/optim/local_convergence.py
portia_grn-0.0.5.dist-info/METADATA
portia_grn-0.0.5.dist-info/WHEEL
portia_grn-0.0.5.dist-info/top_level.txt
portia_grn-0.0.5.dist-info/RECORD
