Metadata-Version: 2.1
Name: portia-grn
Version: 0.0.5
Summary: PORTIA: Fast and Accurate Inference of Gene Regulatory Networks through Robust Precision Matrix Estimation
Home-page: https://github.com/AntoinePassemiers/PORTIA
Author: Antoine Passemiers
Author-email: antoine.passemiers@kuleuven.be
License: UNKNOWN
Platform: UNKNOWN
Classifier: Programming Language :: Python :: 3
Classifier: License :: OSI Approved :: GNU General Public License v2 (GPLv2)
Classifier: Operating System :: OS Independent
Requires-Python: >=3.6
Requires-Dist: numpy (>=1.19.5)
Requires-Dist: scipy
Requires-Dist: scikit-learn
